[
    {
        "id":"1",
        "link":"http://server7.mp3quran.net/basit/001.mp3",
        "name":"الفاتحه"
    },
    {
        "id":"2",
        "link":"http://server7.mp3quran.net/basit/002.mp3",
        "name":"البقره"
    },
    {
        "id":"3",
        "link":"http://server7.mp3quran.net/basit/003.mp3",
        "name":"العمران"
    },    {
        "id":"4",
        "link":"http://server7.mp3quran.net/basit/004.mp3",
        "name":"النساء"
    },
    {
        "id":"5",
        "link":"http://server7.mp3quran.net/basit/005.mp3",
        "name":"المائده"
    },
    {
        "id":"6",
        "link":"http://server7.mp3quran.net/basit/006.mp3",
        "name":"الانعام"
    },
    {
        "id":"7",
        "link":"http://server7.mp3quran.net/basit/007.mp3",
        "name":"الاعراف"
    },
    {
        "id":"9",
        "link":"http://server7.mp3quran.net/basit/008.mp3",
        "name":"الانفال"
    },
    {
        "id":"10",
        "link":"http://server7.mp3quran.net/basit/009.mp3",
        "name":"التوبه"
    },
    {
        "id":"11",
        "link":"http://server7.mp3quran.net/basit/010.mp3",
        "name":"يونس"
    },
    {
        "id":"12",
        "link":"http://server7.mp3quran.net/basit/011.mp3",
        "name":"هود"
    },
    {
        "id":"13",
        "link":"http://server7.mp3quran.net/basit/012.mp3",
        "name":"يوسف"
    },
    {
        "id":"14",
        "link":"http://server7.mp3quran.net/basit/013.mp3",
        "name":"الرعد"
    },
    {
        "id":"15",
        "link":"http://server7.mp3quran.net/basit/014.mp3",
        "name":"ابرهيم"
    },
    {
        "id":"16",
        "link":"http://server7.mp3quran.net/basit/015.mp3",
        "name":"الحجر"
    },
    {
        "id":"17",
        "link":"http://server7.mp3quran.net/basit/016.mp3",
        "name":"النحل"
    },
    {
        "id":"18",
        "link":"http://server7.mp3quran.net/basit/017.mp3",
        "name":"الاسراء"
    },
    {
        "id":"19",
        "link":"http://server7.mp3quran.net/basit/018.mp3",
        "name":"الكهف"
    },
    {
        "id":"20",
        "link":"http://server7.mp3quran.net/basit/019.mp3",
        "name":"مريم"
    },
    {
        "id":"21",
        "link":"http://server7.mp3quran.net/basit/020.mp3",
        "name":"طه"
    },
    {
        "id":"22",
        "link":"http://server7.mp3quran.net/basit/021.mp3",
        "name":"الانبياء"
    },
    {
        "id":"23",
        "link":"http://server7.mp3quran.net/basit/022.mp3",
        "name":"الحج"
    },
    {
        "id":"24",
        "link":"http://server7.mp3quran.net/basit/023.mp3",
        "name":"المؤمنون"
    },
    {
        "id":"25",
        "link":"http://server7.mp3quran.net/basit/024.mp3",
        "name":"النور"
    },
    {
        "id":"26",
        "link":"http://server7.mp3quran.net/basit/025.mp3",
        "name":"الفرقان"
    },
    {
        "id":"27",
        "link":"http://server7.mp3quran.net/basit/026.mp3",
        "name":"الشعراء"
    },
    {
        "id":"28",
        "link":"http://server7.mp3quran.net/basit/027.mp3",
        "name":"النمل"
    },
    {
        "id":"29",
        "link":"http://server7.mp3quran.net/basit/028.mp3",
        "name":"القصص"
    },
    {
        "id":"30",
        "link":"http://server7.mp3quran.net/basit/029.mp3",
        "name":"العنكبوت"
    },
    {
        "id":"31",
        "link":"http://server7.mp3quran.net/basit/030.mp3",
        "name":"الروم"
    },
    {
        "id":"32",
        "link":"http://server7.mp3quran.net/basit/031.mp3",
        "name":"لقمان"
    },
    {
        "id":"32",
        "link":"http://server7.mp3quran.net/basit/032.mp3",
        "name":"السجده"
    },
    {
        "id":"33",
        "link":"http://server7.mp3quran.net/basit/033.mp3",
        "name":"الاحزاب"
    },
    {
        "id":"34",
        "link":"http://server7.mp3quran.net/basit/034.mp3",
        "name":"سباء"
    },
    {
        "id":"35",
        "link":"http://server7.mp3quran.net/basit/035.mp3",
        "name":"فاطر"
    },
    {
        "id":"36",
        "link":"http://server7.mp3quran.net/basit/036.mp3",
        "name":"يس"
    },
    {
        "id":"37",
        "link":"http://server7.mp3quran.net/basit/037.mp3",
        "name":"الصافات"
    },
    {
        "id":"38",
        "link":"http://server7.mp3quran.net/basit/038.mp3",
        "name":"ص"
    },
    {
        "id":"39",
        "link":"http://server7.mp3quran.net/basit/039.mp3",
        "name":"الزمر"
    },
    {
        "id":"40",
        "link":"http://server7.mp3quran.net/basit/040.mp3",
        "name":"غافر"
    },
    {
        "id":"41",
        "link":"http://server7.mp3quran.net/basit/041.mp3",
        "name":"فصلت"
    },
    {
        "id":"42",
        "link":"http://server7.mp3quran.net/basit/042.mp3",
        "name":"الشوري"
    },
    {
        "id":"43",
        "link":"http://server7.mp3quran.net/basit/043.mp3",
        "name":"الزخرف"
    },
    {
        "id":"44",
        "link":"http://server7.mp3quran.net/basit/044.mp3",
        "name":"الدخان"
    },
    {
        "id":"45",
        "link":"http://server7.mp3quran.net/basit/045.mp3",
        "name":"الجاثيه"
    },
    {
        "id":"46",
        "link":"http://server7.mp3quran.net/basit/046.mp3",
        "name":"الاحقاف"
    },
    {
        "id":"47",
        "link":"http://server7.mp3quran.net/basit/047.mp3",
        "name":"محمد"
    },
    {
        "id":"48",
        "link":"http://server7.mp3quran.net/basit/048.mp3",
        "name":"الفتح"
    },
    {
        "id":"49",
        "link":"http://server7.mp3quran.net/basit/049.mp3",
        "name":"الحجرات"
    },
    {
        "id":"50",
        "link":"http://server7.mp3quran.net/basit/050.mp3",
        "name":"ق"
    }
]